{
  "base_layer": [
    {
      "parent": "little_big_redstone:block/sticky_note_base",
      "textures": {
        "texture": "little_big_redstone:block/sticky_note/pink"
      }
    }
  ],
  "loader": "little_big_redstone:sticky_note_entity",
  "text_layer": [
    {
      "parent": "little_big_redstone:block/sticky_note_text",
      "textures": {
        "texture": "little_big_redstone:block/sticky_note/text"
      }
    }
  ],
  "textures": {
    "particle": "little_big_redstone:block/sticky_note/pink"
  }
}